bg_distributions_zs/Binomialdistribution.py
bg_distributions_zs/Gaussiandistribution.py
bg_distributions_zs/Generaldistribution.py
bg_distributions_zs/__init__.py
bg_distributions_zs-0.1.dist-info/DESCRIPTION.rst
bg_distributions_zs-0.1.dist-info/METADATA
bg_distributions_zs-0.1.dist-info/RECORD
bg_distributions_zs-0.1.dist-info/WHEEL
bg_distributions_zs-0.1.dist-info/metadata.json
bg_distributions_zs-0.1.dist-info/top_level.txt
